{
  "date": "2026-07-06",
  "lastUpdated": "12:34 AM, 05 July 2026",
  "shows": [
    {
      "movie_id": "yakpqPfo6j8XEooh9ndzy8",
      "movie_name": "Alpha",
      "show_id": "176030:qfx-labim",
      "venue": "qfx-labim",
      "theatre": "QFX Labim - AUDI 2",
      "date": "2026-07-06T13:30:00+05:45",
      "time": "",
      "seats": 180,
      "sold": 0,
      "reserved": 0,
      "available": 180,
      "gross": 0,
      "occupancy_percent": 0.0
    },
    {
      "movie_id": "yakpqPfo6j8XEooh9ndzy8",
      "movie_name": "Alpha",
      "show_id": "176031:qfx-labim",
      "venue": "qfx-labim",
      "theatre": "QFX Labim - AUDI 3",
      "date": "2026-07-06T18:30:00+05:45",
      "time": "",
      "seats": 183,
      "sold": 2,
      "reserved": 0,
      "available": 181,
      "gross": 780,
      "occupancy_percent": 1.09
    },
    {
      "movie_id": "yakpqPfo6j8XEooh9ndzy8",
      "movie_name": "Alpha",
      "show_id": "63459:big-movies",
      "venue": "big-movies",
      "theatre": "Big Movies - Audi 3",
      "date": "2026-07-06T14:45:00+05:45",
      "time": "",
      "seats": 349,
      "sold": 0,
      "reserved": 50,
      "available": 299,
      "gross": 20000,
      "occupancy_percent": 14.33
    },
    {
      "movie_id": "yakpqPfo6j8XEooh9ndzy8",
      "movie_name": "Alpha",
      "show_id": "63460:big-movies",
      "venue": "big-movies",
      "theatre": "Big Movies - Audi 3",
      "date": "2026-07-06T17:30:00+05:45",
      "time": "",
      "seats": 349,
      "sold": 0,
      "reserved": 50,
      "available": 299,
      "gross": 20000,
      "occupancy_percent": 14.33
    },
    {
      "movie_id": "yakpqPfo6j8XEooh9ndzy8",
      "movie_name": "Alpha",
      "show_id": "63461:big-movies",
      "venue": "big-movies",
      "theatre": "Big Movies - Audi 3",
      "date": "2026-07-06T20:15:00+05:45",
      "time": "",
      "seats": 349,
      "sold": 0,
      "reserved": 50,
      "available": 299,
      "gross": 20000,
      "occupancy_percent": 14.33
    },
    {
      "movie_id": "yakpqPfo6j8XEooh9ndzy8",
      "movie_name": "Alpha",
      "show_id": "63462:big-movies",
      "venue": "big-movies",
      "theatre": "Big Movies - Audi 2",
      "date": "2026-07-06T08:00:00+05:45",
      "time": "",
      "seats": 270,
      "sold": 0,
      "reserved": 50,
      "available": 220,
      "gross": 10000,
      "occupancy_percent": 18.52
    },
    {
      "movie_id": "yakpqPfo6j8XEooh9ndzy8",
      "movie_name": "Alpha",
      "show_id": "63458:big-movies",
      "venue": "big-movies",
      "theatre": "Big Movies - Audi 3",
      "date": "2026-07-06T12:00:00+05:45",
      "time": "",
      "seats": 349,
      "sold": 0,
      "reserved": 50,
      "available": 299,
      "gross": 20000,
      "occupancy_percent": 14.33
    },
    {
      "movie_id": "yakpqPfo6j8XEooh9ndzy8",
      "movie_name": "Alpha",
      "show_id": "175966:qfx-durbar",
      "venue": "qfx-durbar",
      "theatre": "QFX Durbar - AUDI 1",
      "date": "2026-07-06T20:15:00+05:45",
      "time": "",
      "seats": 53,
      "sold": 0,
      "reserved": 0,
      "available": 53,
      "gross": 0,
      "occupancy_percent": 0.0
    },
    {
      "movie_id": "yakpqPfo6j8XEooh9ndzy8",
      "movie_name": "Alpha",
      "show_id": "175888:qfx-civil",
      "venue": "qfx-civil",
      "theatre": "QFX Civil - AUDI 01",
      "date": "2026-07-06T12:30:00+05:45",
      "time": "",
      "seats": 519,
      "sold": 0,
      "reserved": 0,
      "available": 519,
      "gross": 0,
      "occupancy_percent": 0.0
    },
    {
      "movie_id": "yakpqPfo6j8XEooh9ndzy8",
      "movie_name": "Alpha",
      "show_id": "176041:qfx-chhaya",
      "venue": "qfx-chhaya",
      "theatre": "QFX Chhaya - AUDI 2",
      "date": "2026-07-06T19:45:00+05:45",
      "time": "",
      "seats": 150,
      "sold": 0,
      "reserved": 0,
      "available": 150,
      "gross": 0,
      "occupancy_percent": 0.0
    },
    {
      "movie_id": "yakpqPfo6j8XEooh9ndzy8",
      "movie_name": "Alpha",
      "show_id": "176040:qfx-chhaya",
      "venue": "qfx-chhaya",
      "theatre": "QFX Chhaya - AUDI 2",
      "date": "2026-07-06T16:45:00+05:45",
      "time": "",
      "seats": 150,
      "sold": 0,
      "reserved": 0,
      "available": 150,
      "gross": 0,
      "occupancy_percent": 0.0
    },
    {
      "movie_id": "yakpqPfo6j8XEooh9ndzy8",
      "movie_name": "Alpha",
      "show_id": "175968:qfx-durbar",
      "venue": "qfx-durbar",
      "theatre": "QFX Durbar - AUDI 02",
      "date": "2026-07-06T17:15:00+05:45",
      "time": "",
      "seats": 51,
      "sold": 0,
      "reserved": 0,
      "available": 51,
      "gross": 0,
      "occupancy_percent": 0.0
    },
    {
      "movie_id": "yakpqPfo6j8XEooh9ndzy8",
      "movie_name": "Alpha",
      "show_id": "175889:qfx-civil",
      "venue": "qfx-civil",
      "theatre": "QFX Civil - AUDI 01",
      "date": "2026-07-06T15:45:00+05:45",
      "time": "",
      "seats": 519,
      "sold": 0,
      "reserved": 0,
      "available": 519,
      "gross": 0,
      "occupancy_percent": 0.0
    },
    {
      "movie_id": "yakpqPfo6j8XEooh9ndzy8",
      "movie_name": "Alpha",
      "show_id": "175890:qfx-civil",
      "venue": "qfx-civil",
      "theatre": "QFX Civil - AUDI 01",
      "date": "2026-07-06T19:00:00+05:45",
      "time": "",
      "seats": 519,
      "sold": 0,
      "reserved": 0,
      "available": 519,
      "gross": 0,
      "occupancy_percent": 0.0
    },
    {
      "movie_id": "yakpqPfo6j8XEooh9ndzy8",
      "movie_name": "Alpha",
      "show_id": "75258:fcube",
      "venue": "fcube",
      "theatre": "FCube Cinemas - Cube 1",
      "date": "2026-07-06T18:45:00+05:45",
      "time": "",
      "seats": 210,
      "sold": 0,
      "reserved": 10,
      "available": 200,
      "gross": 3800,
      "occupancy_percent": 4.76
    },
    {
      "movie_id": "yakpqPfo6j8XEooh9ndzy8",
      "movie_name": "Alpha",
      "show_id": "75255:fcube",
      "venue": "fcube",
      "theatre": "FCube Cinemas - Cube 3",
      "date": "2026-07-06T15:30:00+05:45",
      "time": "",
      "seats": 212,
      "sold": 0,
      "reserved": 10,
      "available": 202,
      "gross": 4800,
      "occupancy_percent": 4.72
    },
    {
      "movie_id": "yakpqPfo6j8XEooh9ndzy8",
      "movie_name": "Alpha",
      "show_id": "75250:fcube",
      "venue": "fcube",
      "theatre": "FCube Cinemas - Cube 1",
      "date": "2026-07-06T11:30:00+05:45",
      "time": "",
      "seats": 210,
      "sold": 0,
      "reserved": 10,
      "available": 200,
      "gross": 3800,
      "occupancy_percent": 4.76
    },
    {
      "movie_id": "yakpqPfo6j8XEooh9ndzy8",
      "movie_name": "Alpha",
      "show_id": "4571:kirtipur-cineplex",
      "venue": "kirtipur-cineplex",
      "theatre": "Kirtipur Cineplex - Audi-2",
      "date": "2026-07-06T11:15:00+05:45",
      "time": "",
      "seats": 101,
      "sold": 0,
      "reserved": 0,
      "available": 101,
      "gross": 0,
      "occupancy_percent": 0.0
    },
    {
      "movie_id": "yakpqPfo6j8XEooh9ndzy8",
      "movie_name": "Alpha",
      "show_id": "4574:kirtipur-cineplex",
      "venue": "kirtipur-cineplex",
      "theatre": "Kirtipur Cineplex - Audi-2",
      "date": "2026-07-06T19:45:00+05:45",
      "time": "",
      "seats": 101,
      "sold": 0,
      "reserved": 0,
      "available": 101,
      "gross": 0,
      "occupancy_percent": 0.0
    },
    {
      "movie_id": "yakpqPfo6j8XEooh9ndzy8",
      "movie_name": "Alpha",
      "show_id": "175929:qfx-square-mall",
      "venue": "qfx-square-mall",
      "theatre": "QFX City Square Mall - Audi 2",
      "date": "2026-07-06T16:30:00+05:45",
      "time": "",
      "seats": 165,
      "sold": 0,
      "reserved": 0,
      "available": 165,
      "gross": 0,
      "occupancy_percent": 0.0
    },
    {
      "movie_id": "yakpqPfo6j8XEooh9ndzy8",
      "movie_name": "Alpha",
      "show_id": "175941:qfx-square-mall",
      "venue": "qfx-square-mall",
      "theatre": "QFX City Square Mall - Audi 2",
      "date": "2026-07-06T19:30:00+05:45",
      "time": "",
      "seats": 165,
      "sold": 0,
      "reserved": 0,
      "available": 165,
      "gross": 0,
      "occupancy_percent": 0.0
    },
    {
      "movie_id": "yakpqPfo6j8XEooh9ndzy8",
      "movie_name": "Alpha",
      "show_id": "67932:ini-cinemas-nb-center",
      "venue": "ini-cinemas-nb-center",
      "theatre": "iNi NB Center - Audi -2 (DTS: X)",
      "date": "2026-07-06T14:15:00+05:45",
      "time": "",
      "seats": 210,
      "sold": 0,
      "reserved": 0,
      "available": 210,
      "gross": 0,
      "occupancy_percent": 0.0
    },
    {
      "movie_id": "yakpqPfo6j8XEooh9ndzy8",
      "movie_name": "Alpha",
      "show_id": "67908:ini-lotse-ktm",
      "venue": "ini-lotse-ktm",
      "theatre": "iNi Lotse Mall - Audi 2",
      "date": "2026-07-06T20:00:00+05:45",
      "time": "",
      "seats": 240,
      "sold": 0,
      "reserved": 0,
      "available": 240,
      "gross": 0,
      "occupancy_percent": 0.0
    },
    {
      "movie_id": "yakpqPfo6j8XEooh9ndzy8",
      "movie_name": "Alpha",
      "show_id": "67929:ini-cinemas-nb-center",
      "venue": "ini-cinemas-nb-center",
      "theatre": "iNi NB Center - Audi -1 (DTS: X)",
      "date": "2026-07-06T19:00:00+05:45",
      "time": "",
      "seats": 177,
      "sold": 0,
      "reserved": 0,
      "available": 177,
      "gross": 0,
      "occupancy_percent": 0.0
    },
    {
      "movie_id": "yakpqPfo6j8XEooh9ndzy8",
      "movie_name": "Alpha",
      "show_id": "67931:ini-cinemas-nb-center",
      "venue": "ini-cinemas-nb-center",
      "theatre": "iNi NB Center - Audi -2 (DTS: X)",
      "date": "2026-07-06T11:15:00+05:45",
      "time": "",
      "seats": 210,
      "sold": 0,
      "reserved": 0,
      "available": 210,
      "gross": 0,
      "occupancy_percent": 0.0
    },
    {
      "movie_id": "yakpqPfo6j8XEooh9ndzy8",
      "movie_name": "Alpha",
      "show_id": "67901:ini-lotse-ktm",
      "venue": "ini-lotse-ktm",
      "theatre": "iNi Lotse Mall - Audi 1",
      "date": "2026-07-06T11:00:00+05:45",
      "time": "",
      "seats": 240,
      "sold": 0,
      "reserved": 0,
      "available": 240,
      "gross": 0,
      "occupancy_percent": 0.0
    },
    {
      "movie_id": "yakpqPfo6j8XEooh9ndzy8",
      "movie_name": "Alpha",
      "show_id": "67930:ini-cinemas-nb-center",
      "venue": "ini-cinemas-nb-center",
      "theatre": "iNi NB Center - Audi -2 (DTS: X)",
      "date": "2026-07-06T08:00:00+05:45",
      "time": "",
      "seats": 210,
      "sold": 0,
      "reserved": 0,
      "available": 210,
      "gross": 0,
      "occupancy_percent": 0.0
    },
    {
      "movie_id": "yakpqPfo6j8XEooh9ndzy8",
      "movie_name": "Alpha",
      "show_id": "67902:ini-lotse-ktm",
      "venue": "ini-lotse-ktm",
      "theatre": "iNi Lotse Mall - Audi 1",
      "date": "2026-07-06T13:45:00+05:45",
      "time": "",
      "seats": 240,
      "sold": 0,
      "reserved": 0,
      "available": 240,
      "gross": 0,
      "occupancy_percent": 0.0
    },
    {
      "movie_id": "yakpqPfo6j8XEooh9ndzy8",
      "movie_name": "Alpha",
      "show_id": "67907:ini-lotse-ktm",
      "venue": "ini-lotse-ktm",
      "theatre": "iNi Lotse Mall - Audi 2",
      "date": "2026-07-06T17:00:00+05:45",
      "time": "",
      "seats": 240,
      "sold": 0,
      "reserved": 0,
      "available": 240,
      "gross": 0,
      "occupancy_percent": 0.0
    },
    {
      "movie_id": "yakpqPfo6j8XEooh9ndzy8",
      "movie_name": "Alpha",
      "show_id": "175924:qfx-square-mall",
      "venue": "qfx-square-mall",
      "theatre": "QFX City Square Mall - Audi 1",
      "date": "2026-07-06T12:30:00+05:45",
      "time": "",
      "seats": 177,
      "sold": 0,
      "reserved": 0,
      "available": 177,
      "gross": 0,
      "occupancy_percent": 0.0
    },
    {
      "movie_id": "yakpqPfo6j8XEooh9ndzy8",
      "movie_name": "Alpha",
      "show_id": "175940:qs-cinemas",
      "venue": "qs-cinemas",
      "theatre": "QFX Rising Mall - Audi 01",
      "date": "2026-07-06T20:00:00+05:45",
      "time": "",
      "seats": 182,
      "sold": 0,
      "reserved": 0,
      "available": 182,
      "gross": 0,
      "occupancy_percent": 0.0
    },
    {
      "movie_id": "yakpqPfo6j8XEooh9ndzy8",
      "movie_name": "Alpha",
      "show_id": "47910:bsr-movies",
      "venue": "bsr-movies",
      "theatre": "BSR Movies - Atmos 2",
      "date": "2026-07-06T19:00:00+05:45",
      "time": "",
      "seats": 180,
      "sold": 0,
      "reserved": 0,
      "available": 180,
      "gross": 0,
      "occupancy_percent": 0.0
    },
    {
      "movie_id": "yakpqPfo6j8XEooh9ndzy8",
      "movie_name": "Alpha",
      "show_id": "47909:bsr-movies",
      "venue": "bsr-movies",
      "theatre": "BSR Movies - Atmos 2",
      "date": "2026-07-06T16:15:00+05:45",
      "time": "",
      "seats": 180,
      "sold": 0,
      "reserved": 0,
      "available": 180,
      "gross": 0,
      "occupancy_percent": 0.0
    },
    {
      "movie_id": "yakpqPfo6j8XEooh9ndzy8",
      "movie_name": "Alpha",
      "show_id": "47908:bsr-movies",
      "venue": "bsr-movies",
      "theatre": "BSR Movies - Atmos 2",
      "date": "2026-07-06T13:30:00+05:45",
      "time": "",
      "seats": 180,
      "sold": 0,
      "reserved": 0,
      "available": 180,
      "gross": 0,
      "occupancy_percent": 0.0
    },
    {
      "movie_id": "yakpqPfo6j8XEooh9ndzy8",
      "movie_name": "Alpha",
      "show_id": "28119:one-cinemas-kalimati",
      "venue": "one-cinemas-kalimati",
      "theatre": "One Cinemas Kalimati - Audi 1",
      "date": "2026-07-06T09:00:00+05:45",
      "time": "",
      "seats": 151,
      "sold": 14,
      "reserved": 0,
      "available": 137,
      "gross": 2800,
      "occupancy_percent": 9.27
    },
    {
      "movie_id": "yakpqPfo6j8XEooh9ndzy8",
      "movie_name": "Alpha",
      "show_id": "175937:qs-cinemas",
      "venue": "qs-cinemas",
      "theatre": "QFX Rising Mall - Audi 01",
      "date": "2026-07-06T17:00:00+05:45",
      "time": "",
      "seats": 182,
      "sold": 0,
      "reserved": 0,
      "available": 182,
      "gross": 0,
      "occupancy_percent": 0.0
    },
    {
      "movie_id": "yakpqPfo6j8XEooh9ndzy8",
      "movie_name": "Alpha",
      "show_id": "175932:qs-cinemas",
      "venue": "qs-cinemas",
      "theatre": "QFX Rising Mall - Audi 01",
      "date": "2026-07-06T11:30:00+05:45",
      "time": "",
      "seats": 182,
      "sold": 0,
      "reserved": 0,
      "available": 182,
      "gross": 0,
      "occupancy_percent": 0.0
    },
    {
      "movie_id": "yakpqPfo6j8XEooh9ndzy8",
      "movie_name": "Alpha",
      "show_id": "28123:one-cinemas-kalimati",
      "venue": "one-cinemas-kalimati",
      "theatre": "One Cinemas Kalimati - Audi 1",
      "date": "2026-07-06T20:30:00+05:45",
      "time": "",
      "seats": 151,
      "sold": 17,
      "reserved": 0,
      "available": 134,
      "gross": 3400,
      "occupancy_percent": 11.26
    },
    {
      "movie_id": "yakpqPfo6j8XEooh9ndzy8",
      "movie_name": "Alpha",
      "show_id": "28121:one-cinemas-kalimati",
      "venue": "one-cinemas-kalimati",
      "theatre": "One Cinemas Kalimati - Audi 1",
      "date": "2026-07-06T14:45:00+05:45",
      "time": "",
      "seats": 151,
      "sold": 14,
      "reserved": 0,
      "available": 137,
      "gross": 2800,
      "occupancy_percent": 9.27
    },
    {
      "movie_id": "yakpqPfo6j8XEooh9ndzy8",
      "movie_name": "Alpha",
      "show_id": "67892:bishwojyoti-cineplex",
      "venue": "bishwojyoti-cineplex",
      "theatre": "iNi Bishwojyoti Mall - Audi 1",
      "date": "2026-07-06T19:00:00+05:45",
      "time": "",
      "seats": 201,
      "sold": 0,
      "reserved": 0,
      "available": 201,
      "gross": 0,
      "occupancy_percent": 0.0
    },
    {
      "movie_id": "yakpqPfo6j8XEooh9ndzy8",
      "movie_name": "Alpha",
      "show_id": "67891:bishwojyoti-cineplex",
      "venue": "bishwojyoti-cineplex",
      "theatre": "iNi Bishwojyoti Mall - Audi 1",
      "date": "2026-07-06T16:15:00+05:45",
      "time": "",
      "seats": 201,
      "sold": 0,
      "reserved": 0,
      "available": 201,
      "gross": 0,
      "occupancy_percent": 0.0
    },
    {
      "movie_id": "yakpqPfo6j8XEooh9ndzy8",
      "movie_name": "Alpha",
      "show_id": "67889:bishwojyoti-cineplex",
      "venue": "bishwojyoti-cineplex",
      "theatre": "iNi Bishwojyoti Mall - Audi 1",
      "date": "2026-07-06T11:30:00+05:45",
      "time": "",
      "seats": 201,
      "sold": 0,
      "reserved": 0,
      "available": 201,
      "gross": 0,
      "occupancy_percent": 0.0
    },
    {
      "movie_id": "yakpqPfo6j8XEooh9ndzy8",
      "movie_name": "Alpha",
      "show_id": "175905:qfx-jalma",
      "venue": "qfx-jalma",
      "theatre": "QFX Jalma, Narayangarh - AUDI 1",
      "date": "2026-07-06T15:15:00+05:45",
      "time": "",
      "seats": 268,
      "sold": 0,
      "reserved": 0,
      "available": 268,
      "gross": 0,
      "occupancy_percent": 0.0
    },
    {
      "movie_id": "yakpqPfo6j8XEooh9ndzy8",
      "movie_name": "Alpha",
      "show_id": "67900:ini-simara",
      "venue": "ini-simara",
      "theatre": "iNi Simara - Audi 2",
      "date": "2026-07-06T19:15:00+05:45",
      "time": "",
      "seats": 199,
      "sold": 0,
      "reserved": 0,
      "available": 199,
      "gross": 0,
      "occupancy_percent": 0.0
    },
    {
      "movie_id": "yakpqPfo6j8XEooh9ndzy8",
      "movie_name": "Alpha",
      "show_id": "67899:ini-simara",
      "venue": "ini-simara",
      "theatre": "iNi Simara - Audi 2",
      "date": "2026-07-06T16:30:00+05:45",
      "time": "",
      "seats": 199,
      "sold": 0,
      "reserved": 0,
      "available": 199,
      "gross": 0,
      "occupancy_percent": 0.0
    },
    {
      "movie_id": "yakpqPfo6j8XEooh9ndzy8",
      "movie_name": "Alpha",
      "show_id": "176056:chitwan-cineplex",
      "venue": "chitwan-cineplex",
      "theatre": "QFX Cinemas CG Mall - SCREEN 1",
      "date": "2026-07-06T18:45:00+05:45",
      "time": "",
      "seats": 219,
      "sold": 0,
      "reserved": 0,
      "available": 219,
      "gross": 0,
      "occupancy_percent": 0.0
    },
    {
      "movie_id": "yakpqPfo6j8XEooh9ndzy8",
      "movie_name": "Alpha",
      "show_id": "176058:chitwan-cineplex",
      "venue": "chitwan-cineplex",
      "theatre": "QFX Cinemas CG Mall - SCREEN 1",
      "date": "2026-07-06T12:15:00+05:45",
      "time": "",
      "seats": 219,
      "sold": 0,
      "reserved": 0,
      "available": 219,
      "gross": 0,
      "occupancy_percent": 0.0
    },
    {
      "movie_id": "yakpqPfo6j8XEooh9ndzy8",
      "movie_name": "Alpha",
      "show_id": "176079:pokhara-cineplex",
      "venue": "pokhara-cineplex",
      "theatre": "QFX Cinemas Trade Mall - AUDI 1",
      "date": "2026-07-06T19:00:00+05:45",
      "time": "",
      "seats": 359,
      "sold": 0,
      "reserved": 0,
      "available": 359,
      "gross": 0,
      "occupancy_percent": 0.0
    },
    {
      "movie_id": "yakpqPfo6j8XEooh9ndzy8",
      "movie_name": "Alpha",
      "show_id": "67920:ini-qbox-butwal",
      "venue": "ini-qbox-butwal",
      "theatre": "iNi Butwal - Audi 1",
      "date": "2026-07-06T19:30:00+05:45",
      "time": "",
      "seats": 196,
      "sold": 0,
      "reserved": 0,
      "available": 196,
      "gross": 0,
      "occupancy_percent": 0.0
    },
    {
      "movie_id": "yakpqPfo6j8XEooh9ndzy8",
      "movie_name": "Alpha",
      "show_id": "67918:ini-qbox-butwal",
      "venue": "ini-qbox-butwal",
      "theatre": "iNi Butwal - Audi 1",
      "date": "2026-07-06T14:00:00+05:45",
      "time": "",
      "seats": 196,
      "sold": 0,
      "reserved": 0,
      "available": 196,
      "gross": 0,
      "occupancy_percent": 0.0
    },
    {
      "movie_id": "yakpqPfo6j8XEooh9ndzy8",
      "movie_name": "Alpha",
      "show_id": "67917:ini-qbox-butwal",
      "venue": "ini-qbox-butwal",
      "theatre": "iNi Butwal - Audi 1",
      "date": "2026-07-06T11:15:00+05:45",
      "time": "",
      "seats": 196,
      "sold": 0,
      "reserved": 0,
      "available": 196,
      "gross": 0,
      "occupancy_percent": 0.0
    },
    {
      "movie_id": "yakpqPfo6j8XEooh9ndzy8",
      "movie_name": "Alpha",
      "show_id": "176077:pokhara-cineplex",
      "venue": "pokhara-cineplex",
      "theatre": "QFX Cinemas Trade Mall - AUDI 1",
      "date": "2026-07-06T12:15:00+05:45",
      "time": "",
      "seats": 359,
      "sold": 0,
      "reserved": 0,
      "available": 359,
      "gross": 0,
      "occupancy_percent": 0.0
    },
    {
      "movie_id": "yakpqPfo6j8XEooh9ndzy8",
      "movie_name": "Alpha",
      "show_id": "176017:qfx-butwal",
      "venue": "qfx-butwal",
      "theatre": "QFX Butwal - AUDI 1",
      "date": "2026-07-06T15:00:00+05:45",
      "time": "",
      "seats": 176,
      "sold": 0,
      "reserved": 0,
      "available": 176,
      "gross": 0,
      "occupancy_percent": 0.0
    },
    {
      "movie_id": "yakpqPfo6j8XEooh9ndzy8",
      "movie_name": "Alpha",
      "show_id": "67888:ini-cinemas-devchuli",
      "venue": "ini-cinemas-devchuli",
      "theatre": "iNi Devchuli - Audi 1 (DTS: X)",
      "date": "2026-07-06T18:30:00+05:45",
      "time": "",
      "seats": 292,
      "sold": 0,
      "reserved": 0,
      "available": 292,
      "gross": 0,
      "occupancy_percent": 0.0
    },
    {
      "movie_id": "yakpqPfo6j8XEooh9ndzy8",
      "movie_name": "Alpha",
      "show_id": "176026:qfx-one-stop-mall",
      "venue": "qfx-one-stop-mall",
      "theatre": "QFX One Stop, Birtamod - AUDI 1",
      "date": "2026-07-06T15:30:00+05:45",
      "time": "",
      "seats": 138,
      "sold": 0,
      "reserved": 0,
      "available": 138,
      "gross": 0,
      "occupancy_percent": 0.0
    },
    {
      "movie_id": "yakpqPfo6j8XEooh9ndzy8",
      "movie_name": "Alpha",
      "show_id": "176018:qfx-butwal",
      "venue": "qfx-butwal",
      "theatre": "QFX Butwal - AUDI 1",
      "date": "2026-07-06T12:00:00+05:45",
      "time": "",
      "seats": 176,
      "sold": 2,
      "reserved": 0,
      "available": 174,
      "gross": 560,
      "occupancy_percent": 1.14
    },
    {
      "movie_id": "yakpqPfo6j8XEooh9ndzy8",
      "movie_name": "Alpha",
      "show_id": "67886:ini-cinemas-devchuli",
      "venue": "ini-cinemas-devchuli",
      "theatre": "iNi Devchuli - Audi 1 (DTS: X)",
      "date": "2026-07-06T12:00:00+05:45",
      "time": "",
      "seats": 292,
      "sold": 0,
      "reserved": 0,
      "available": 292,
      "gross": 0,
      "occupancy_percent": 0.0
    },
    {
      "movie_id": "yakpqPfo6j8XEooh9ndzy8",
      "movie_name": "Alpha",
      "show_id": "176101:qfx-cineflix-itahari",
      "venue": "qfx-cineflix-itahari",
      "theatre": "QFX Cineflix, Itahari - Audi 1",
      "date": "2026-07-06T11:00:00+05:45",
      "time": "",
      "seats": 134,
      "sold": 0,
      "reserved": 0,
      "available": 134,
      "gross": 0,
      "occupancy_percent": 0.0
    },
    {
      "movie_id": "yakpqPfo6j8XEooh9ndzy8",
      "movie_name": "Alpha",
      "show_id": "67912:ini-bhairahawa-bhatbhateni",
      "venue": "ini-bhairahawa-bhatbhateni",
      "theatre": "iNi Bhairahawa Bhatbhateni - Audi - 1 ( DTS:X )",
      "date": "2026-07-06T19:30:00+05:45",
      "time": "",
      "seats": 198,
      "sold": 0,
      "reserved": 0,
      "available": 198,
      "gross": 0,
      "occupancy_percent": 0.0
    },
    {
      "movie_id": "yakpqPfo6j8XEooh9ndzy8",
      "movie_name": "Alpha",
      "show_id": "176027:qfx-one-stop-mall",
      "venue": "qfx-one-stop-mall",
      "theatre": "QFX One Stop, Birtamod - AUDI 2",
      "date": "2026-07-06T19:30:00+05:45",
      "time": "",
      "seats": 133,
      "sold": 2,
      "reserved": 0,
      "available": 131,
      "gross": 560,
      "occupancy_percent": 1.5
    },
    {
      "movie_id": "yakpqPfo6j8XEooh9ndzy8",
      "movie_name": "Alpha",
      "show_id": "67909:ini-bhairahawa-bhatbhateni",
      "venue": "ini-bhairahawa-bhatbhateni",
      "theatre": "iNi Bhairahawa Bhatbhateni - Audi - 1 ( DTS:X )",
      "date": "2026-07-06T11:15:00+05:45",
      "time": "",
      "seats": 198,
      "sold": 0,
      "reserved": 0,
      "available": 198,
      "gross": 0,
      "occupancy_percent": 0.0
    },
    {
      "movie_id": "yakpqPfo6j8XEooh9ndzy8",
      "movie_name": "Alpha",
      "show_id": "176104:qfx-cineflix-itahari",
      "venue": "qfx-cineflix-itahari",
      "theatre": "QFX Cineflix, Itahari - Audi 1",
      "date": "2026-07-06T14:00:00+05:45",
      "time": "",
      "seats": 134,
      "sold": 0,
      "reserved": 0,
      "available": 134,
      "gross": 0,
      "occupancy_percent": 0.0
    },
    {
      "movie_id": "yakpqPfo6j8XEooh9ndzy8",
      "movie_name": "Alpha",
      "show_id": "67910:ini-bhairahawa-bhatbhateni",
      "venue": "ini-bhairahawa-bhatbhateni",
      "theatre": "iNi Bhairahawa Bhatbhateni - Audi - 1 ( DTS:X )",
      "date": "2026-07-06T14:00:00+05:45",
      "time": "",
      "seats": 198,
      "sold": 0,
      "reserved": 0,
      "available": 198,
      "gross": 0,
      "occupancy_percent": 0.0
    },
    {
      "movie_id": "yakpqPfo6j8XEooh9ndzy8",
      "movie_name": "Alpha",
      "show_id": "176107:qfx-cineflix-itahari",
      "venue": "qfx-cineflix-itahari",
      "theatre": "QFX Cineflix, Itahari - Audi 2",
      "date": "2026-07-06T18:30:00+05:45",
      "time": "",
      "seats": 134,
      "sold": 0,
      "reserved": 0,
      "available": 134,
      "gross": 0,
      "occupancy_percent": 0.0
    },
    {
      "movie_id": "yakpqPfo6j8XEooh9ndzy8",
      "movie_name": "Alpha",
      "show_id": "2470:pathivara-cine-plaza",
      "venue": "pathivara-cine-plaza",
      "theatre": "Pathivara Cineplaza - Birtamode - Hall-A",
      "date": "2026-07-06T19:00:00+05:45",
      "time": "",
      "seats": 268,
      "sold": 0,
      "reserved": 0,
      "available": 268,
      "gross": 0,
      "occupancy_percent": 0.0
    },
    {
      "movie_id": "yakpqPfo6j8XEooh9ndzy8",
      "movie_name": "Alpha",
      "show_id": "2468:pathivara-cine-plaza",
      "venue": "pathivara-cine-plaza",
      "theatre": "Pathivara Cineplaza - Birtamode - Hall-A",
      "date": "2026-07-06T11:30:00+05:45",
      "time": "",
      "seats": 268,
      "sold": 0,
      "reserved": 0,
      "available": 268,
      "gross": 0,
      "occupancy_percent": 0.0
    },
    {
      "movie_id": "5dQ3HuQDoeHtCbLKrNVxZ9",
      "movie_name": "Baby Do Die Do",
      "show_id": "67904:ini-lotse-ktm",
      "venue": "ini-lotse-ktm",
      "theatre": "iNi Lotse Mall - Audi 1",
      "date": "2026-07-06T19:30:00+05:45",
      "time": "",
      "seats": 240,
      "sold": 0,
      "reserved": 0,
      "available": 240,
      "gross": 0,
      "occupancy_percent": 0.0
    },
    {
      "movie_id": "5dQ3HuQDoeHtCbLKrNVxZ9",
      "movie_name": "Baby Do Die Do",
      "show_id": "67895:bishwojyoti-cineplex",
      "venue": "bishwojyoti-cineplex",
      "theatre": "iNi Bishwojyoti Mall - Audi 2",
      "date": "2026-07-06T17:30:00+05:45",
      "time": "",
      "seats": 89,
      "sold": 0,
      "reserved": 0,
      "available": 89,
      "gross": 0,
      "occupancy_percent": 0.0
    },
    {
      "movie_id": "5dQ3HuQDoeHtCbLKrNVxZ9",
      "movie_name": "Baby Do Die Do",
      "show_id": "67933:ini-cinemas-nb-center",
      "venue": "ini-cinemas-nb-center",
      "theatre": "iNi NB Center - Audi -2 (DTS: X)",
      "date": "2026-07-06T17:00:00+05:45",
      "time": "",
      "seats": 210,
      "sold": 0,
      "reserved": 0,
      "available": 210,
      "gross": 0,
      "occupancy_percent": 0.0
    },
    {
      "movie_id": "5dQ3HuQDoeHtCbLKrNVxZ9",
      "movie_name": "Baby Do Die Do",
      "show_id": "47907:bsr-movies",
      "venue": "bsr-movies",
      "theatre": "BSR Movies - Atmos 2",
      "date": "2026-07-06T11:00:00+05:45",
      "time": "",
      "seats": 180,
      "sold": 0,
      "reserved": 0,
      "available": 180,
      "gross": 0,
      "occupancy_percent": 0.0
    },
    {
      "movie_id": "5dQ3HuQDoeHtCbLKrNVxZ9",
      "movie_name": "Baby Do Die Do",
      "show_id": "4567:kirtipur-cineplex",
      "venue": "kirtipur-cineplex",
      "theatre": "Kirtipur Cineplex - Audi-1",
      "date": "2026-07-06T11:00:00+05:45",
      "time": "",
      "seats": 285,
      "sold": 0,
      "reserved": 0,
      "available": 285,
      "gross": 0,
      "occupancy_percent": 0.0
    },
    {
      "movie_id": "5dQ3HuQDoeHtCbLKrNVxZ9",
      "movie_name": "Baby Do Die Do",
      "show_id": "28127:one-cinemas-kalimati",
      "venue": "one-cinemas-kalimati",
      "theatre": "One Cinemas Kalimati - Audi 2",
      "date": "2026-07-06T18:00:00+05:45",
      "time": "",
      "seats": 136,
      "sold": 14,
      "reserved": 0,
      "available": 122,
      "gross": 2800,
      "occupancy_percent": 10.29
    },
    {
      "movie_id": "5dQ3HuQDoeHtCbLKrNVxZ9",
      "movie_name": "Baby Do Die Do",
      "show_id": "175933:qs-cinemas",
      "venue": "qs-cinemas",
      "theatre": "QFX Rising Mall - Audi 2",
      "date": "2026-07-06T13:15:00+05:45",
      "time": "",
      "seats": 129,
      "sold": 0,
      "reserved": 0,
      "available": 129,
      "gross": 0,
      "occupancy_percent": 0.0
    },
    {
      "movie_id": "5dQ3HuQDoeHtCbLKrNVxZ9",
      "movie_name": "Baby Do Die Do",
      "show_id": "175925:qfx-square-mall",
      "venue": "qfx-square-mall",
      "theatre": "QFX City Square Mall - Audi 03",
      "date": "2026-07-06T20:00:00+05:45",
      "time": "",
      "seats": 139,
      "sold": 0,
      "reserved": 0,
      "available": 139,
      "gross": 0,
      "occupancy_percent": 0.0
    },
    {
      "movie_id": "5dQ3HuQDoeHtCbLKrNVxZ9",
      "movie_name": "Baby Do Die Do",
      "show_id": "176042:qfx-labim",
      "venue": "qfx-labim",
      "theatre": "QFX Labim - AUDI 2",
      "date": "2026-07-06T16:45:00+05:45",
      "time": "",
      "seats": 180,
      "sold": 0,
      "reserved": 0,
      "available": 180,
      "gross": 0,
      "occupancy_percent": 0.0
    },
    {
      "movie_id": "5dQ3HuQDoeHtCbLKrNVxZ9",
      "movie_name": "Baby Do Die Do",
      "show_id": "176044:qfx-chhaya",
      "venue": "qfx-chhaya",
      "theatre": "QFX Chhaya - AUDI 03",
      "date": "2026-07-06T15:30:00+05:45",
      "time": "",
      "seats": 110,
      "sold": 0,
      "reserved": 0,
      "available": 110,
      "gross": 0,
      "occupancy_percent": 0.0
    },
    {
      "movie_id": "5dQ3HuQDoeHtCbLKrNVxZ9",
      "movie_name": "Baby Do Die Do",
      "show_id": "67887:ini-cinemas-devchuli",
      "venue": "ini-cinemas-devchuli",
      "theatre": "iNi Devchuli - Audi 1 (DTS: X)",
      "date": "2026-07-06T15:15:00+05:45",
      "time": "",
      "seats": 292,
      "sold": 0,
      "reserved": 0,
      "available": 292,
      "gross": 0,
      "occupancy_percent": 0.0
    },
    {
      "movie_id": "5dQ3HuQDoeHtCbLKrNVxZ9",
      "movie_name": "Baby Do Die Do",
      "show_id": "67919:ini-qbox-butwal",
      "venue": "ini-qbox-butwal",
      "theatre": "iNi Butwal - Audi 1",
      "date": "2026-07-06T17:00:00+05:45",
      "time": "",
      "seats": 196,
      "sold": 0,
      "reserved": 0,
      "available": 196,
      "gross": 0,
      "occupancy_percent": 0.0
    },
    {
      "movie_id": "5dQ3HuQDoeHtCbLKrNVxZ9",
      "movie_name": "Baby Do Die Do",
      "show_id": "176076:pokhara-cineplex",
      "venue": "pokhara-cineplex",
      "theatre": "QFX Cinemas Trade Mall - AUDI 2",
      "date": "2026-07-06T19:30:00+05:45",
      "time": "",
      "seats": 231,
      "sold": 0,
      "reserved": 0,
      "available": 231,
      "gross": 0,
      "occupancy_percent": 0.0
    },
    {
      "movie_id": "5dQ3HuQDoeHtCbLKrNVxZ9",
      "movie_name": "Baby Do Die Do",
      "show_id": "67911:ini-bhairahawa-bhatbhateni",
      "venue": "ini-bhairahawa-bhatbhateni",
      "theatre": "iNi Bhairahawa Bhatbhateni - Audi - 1 ( DTS:X )",
      "date": "2026-07-06T17:00:00+05:45",
      "time": "",
      "seats": 198,
      "sold": 0,
      "reserved": 0,
      "available": 198,
      "gross": 0,
      "occupancy_percent": 0.0
    },
    {
      "movie_id": "5dQ3HuQDoeHtCbLKrNVxZ9",
      "movie_name": "Baby Do Die Do",
      "show_id": "176061:chitwan-cineplex",
      "venue": "chitwan-cineplex",
      "theatre": "QFX Cinemas CG Mall - SCREEN 2",
      "date": "2026-07-06T18:30:00+05:45",
      "time": "",
      "seats": 143,
      "sold": 0,
      "reserved": 0,
      "available": 143,
      "gross": 0,
      "occupancy_percent": 0.0
    },
    {
      "movie_id": "5dQ3HuQDoeHtCbLKrNVxZ9",
      "movie_name": "Baby Do Die Do",
      "show_id": "175910:qfx-jalma",
      "venue": "qfx-jalma",
      "theatre": "QFX Jalma, Narayangarh - AUDI 2",
      "date": "2026-07-06T15:30:00+05:45",
      "time": "",
      "seats": 265,
      "sold": 0,
      "reserved": 0,
      "available": 265,
      "gross": 0,
      "occupancy_percent": 0.0
    },
    {
      "movie_id": "5dQ3HuQDoeHtCbLKrNVxZ9",
      "movie_name": "Baby Do Die Do",
      "show_id": "2471:pathivara-cine-plaza",
      "venue": "pathivara-cine-plaza",
      "theatre": "Pathivara Cineplaza - Birtamode - Hall-B",
      "date": "2026-07-06T12:00:00+05:45",
      "time": "",
      "seats": 190,
      "sold": 0,
      "reserved": 0,
      "available": 190,
      "gross": 0,
      "occupancy_percent": 0.0
    },
    {
      "movie_id": "UmvcdW6TPxabGYNL2jgMye",
      "movie_name": "Nagabandham - The Secret Treasure",
      "show_id": "67896:bishwojyoti-cineplex",
      "venue": "bishwojyoti-cineplex",
      "theatre": "iNi Bishwojyoti Mall - Audi 2",
      "date": "2026-07-06T19:45:00+05:45",
      "time": "",
      "seats": 89,
      "sold": 0,
      "reserved": 0,
      "available": 89,
      "gross": 0,
      "occupancy_percent": 0.0
    },
    {
      "movie_id": "UmvcdW6TPxabGYNL2jgMye",
      "movie_name": "Nagabandham - The Secret Treasure",
      "show_id": "67926:ini-cinemas-nb-center",
      "venue": "ini-cinemas-nb-center",
      "theatre": "iNi NB Center - Audi -1 (DTS: X)",
      "date": "2026-07-06T10:30:00+05:45",
      "time": "",
      "seats": 177,
      "sold": 0,
      "reserved": 0,
      "available": 177,
      "gross": 0,
      "occupancy_percent": 0.0
    },
    {
      "movie_id": "UmvcdW6TPxabGYNL2jgMye",
      "movie_name": "Nagabandham - The Secret Treasure",
      "show_id": "63470:big-movies",
      "venue": "big-movies",
      "theatre": "Big Movies - Audi 1",
      "date": "2026-07-06T16:00:00+05:45",
      "time": "",
      "seats": 279,
      "sold": 0,
      "reserved": 42,
      "available": 237,
      "gross": 16800,
      "occupancy_percent": 15.05
    },
    {
      "movie_id": "UmvcdW6TPxabGYNL2jgMye",
      "movie_name": "Nagabandham - The Secret Treasure",
      "show_id": "175999:qfx-durbar",
      "venue": "qfx-durbar",
      "theatre": "QFX Durbar - AUDI 02",
      "date": "2026-07-06T13:30:00+05:45",
      "time": "",
      "seats": 51,
      "sold": 0,
      "reserved": 0,
      "available": 51,
      "gross": 0,
      "occupancy_percent": 0.0
    },
    {
      "movie_id": "UmvcdW6TPxabGYNL2jgMye",
      "movie_name": "Nagabandham - The Secret Treasure",
      "show_id": "175994:qs-cinemas",
      "venue": "qs-cinemas",
      "theatre": "QFX Rising Mall - Audi 2",
      "date": "2026-07-06T19:30:00+05:45",
      "time": "",
      "seats": 129,
      "sold": 0,
      "reserved": 0,
      "available": 129,
      "gross": 0,
      "occupancy_percent": 0.0
    },
    {
      "movie_id": "UmvcdW6TPxabGYNL2jgMye",
      "movie_name": "Nagabandham - The Secret Treasure",
      "show_id": "28128:one-cinemas-kalimati",
      "venue": "one-cinemas-kalimati",
      "theatre": "One Cinemas Kalimati - Audi 2",
      "date": "2026-07-06T20:15:00+05:45",
      "time": "",
      "seats": 136,
      "sold": 14,
      "reserved": 0,
      "available": 122,
      "gross": 2800,
      "occupancy_percent": 10.29
    },
    {
      "movie_id": "UmvcdW6TPxabGYNL2jgMye",
      "movie_name": "Nagabandham - The Secret Treasure",
      "show_id": "176049:qfx-labim",
      "venue": "qfx-labim",
      "theatre": "QFX Labim - AUDI 1",
      "date": "2026-07-06T18:45:00+05:45",
      "time": "",
      "seats": 182,
      "sold": 2,
      "reserved": 0,
      "available": 180,
      "gross": 780,
      "occupancy_percent": 1.1
    },
    {
      "movie_id": "UmvcdW6TPxabGYNL2jgMye",
      "movie_name": "Nagabandham - The Secret Treasure",
      "show_id": "67924:ini-qbox-butwal",
      "venue": "ini-qbox-butwal",
      "theatre": "iNi Butwal - Audi 2",
      "date": "2026-07-06T19:15:00+05:45",
      "time": "",
      "seats": 196,
      "sold": 0,
      "reserved": 0,
      "available": 196,
      "gross": 0,
      "occupancy_percent": 0.0
    },
    {
      "movie_id": "UmvcdW6TPxabGYNL2jgMye",
      "movie_name": "Nagabandham - The Secret Treasure",
      "show_id": "67913:ini-bhairahawa-bhatbhateni",
      "venue": "ini-bhairahawa-bhatbhateni",
      "theatre": "iNi Bhairahawa Bhatbhateni - Audi - 2 ( DTS:X )",
      "date": "2026-07-06T11:00:00+05:45",
      "time": "",
      "seats": 198,
      "sold": 0,
      "reserved": 0,
      "available": 198,
      "gross": 0,
      "occupancy_percent": 0.0
    },
    {
      "movie_id": "UmvcdW6TPxabGYNL2jgMye",
      "movie_name": "Nagabandham - The Secret Treasure",
      "show_id": "175990:qfx-jalma",
      "venue": "qfx-jalma",
      "theatre": "QFX Jalma, Narayangarh - AUDI 1",
      "date": "2026-07-06T18:30:00+05:45",
      "time": "",
      "seats": 268,
      "sold": 0,
      "reserved": 0,
      "available": 268,
      "gross": 0,
      "occupancy_percent": 0.0
    },
    {
      "movie_id": "UmvcdW6TPxabGYNL2jgMye",
      "movie_name": "Nagabandham - The Secret Treasure",
      "show_id": "176015:qfx-civil",
      "venue": "qfx-civil",
      "theatre": "QFX Civil - AUDI 03",
      "date": "2026-07-06T18:30:00+05:45",
      "time": "",
      "seats": 259,
      "sold": 0,
      "reserved": 0,
      "available": 259,
      "gross": 0,
      "occupancy_percent": 0.0
    },
    {
      "movie_id": "UmvcdW6TPxabGYNL2jgMye",
      "movie_name": "Nagabandham - The Secret Treasure",
      "show_id": "63467:big-movies",
      "venue": "big-movies",
      "theatre": "Big Movies - Audi 1",
      "date": "2026-07-06T08:15:00+05:45",
      "time": "",
      "seats": 279,
      "sold": 0,
      "reserved": 42,
      "available": 237,
      "gross": 8400,
      "occupancy_percent": 15.05
    },
    {
      "movie_id": "UmvcdW6TPxabGYNL2jgMye",
      "movie_name": "Nagabandham - The Secret Treasure",
      "show_id": "176078:pokhara-cineplex",
      "venue": "pokhara-cineplex",
      "theatre": "QFX Cinemas Trade Mall - AUDI 1",
      "date": "2026-07-06T15:15:00+05:45",
      "time": "",
      "seats": 359,
      "sold": 0,
      "reserved": 0,
      "available": 359,
      "gross": 0,
      "occupancy_percent": 0.0
    },
    {
      "movie_id": "UmvcdW6TPxabGYNL2jgMye",
      "movie_name": "Nagabandham - The Secret Treasure",
      "show_id": "176004:qfx-square-mall",
      "venue": "qfx-square-mall",
      "theatre": "QFX City Square Mall - Audi 03",
      "date": "2026-07-06T11:15:00+05:45",
      "time": "",
      "seats": 139,
      "sold": 0,
      "reserved": 0,
      "available": 139,
      "gross": 0,
      "occupancy_percent": 0.0
    },
    {
      "movie_id": "UmvcdW6TPxabGYNL2jgMye",
      "movie_name": "Nagabandham - The Secret Treasure",
      "show_id": "2469:pathivara-cine-plaza",
      "venue": "pathivara-cine-plaza",
      "theatre": "Pathivara Cineplaza - Birtamode - Hall-A",
      "date": "2026-07-06T14:15:00+05:45",
      "time": "",
      "seats": 268,
      "sold": 0,
      "reserved": 0,
      "available": 268,
      "gross": 0,
      "occupancy_percent": 0.0
    },
    {
      "movie_id": "7XxkGNYKcCbMMjHQsDeJ3M",
      "movie_name": "Welcome to the Jungle",
      "show_id": "175967:qfx-durbar",
      "venue": "qfx-durbar",
      "theatre": "QFX Durbar - AUDI 02",
      "date": "2026-07-06T20:15:00+05:45",
      "time": "",
      "seats": 51,
      "sold": 0,
      "reserved": 0,
      "available": 51,
      "gross": 0,
      "occupancy_percent": 0.0
    },
    {
      "movie_id": "7XxkGNYKcCbMMjHQsDeJ3M",
      "movie_name": "Welcome to the Jungle",
      "show_id": "176043:qfx-chhaya",
      "venue": "qfx-chhaya",
      "theatre": "QFX Chhaya - AUDI 03",
      "date": "2026-07-06T12:00:00+05:45",
      "time": "",
      "seats": 110,
      "sold": 0,
      "reserved": 0,
      "available": 110,
      "gross": 0,
      "occupancy_percent": 0.0
    },
    {
      "movie_id": "7XxkGNYKcCbMMjHQsDeJ3M",
      "movie_name": "Welcome to the Jungle",
      "show_id": "63466:big-movies",
      "venue": "big-movies",
      "theatre": "Big Movies - Audi 2",
      "date": "2026-07-06T20:00:00+05:45",
      "time": "",
      "seats": 270,
      "sold": 0,
      "reserved": 50,
      "available": 220,
      "gross": 20000,
      "occupancy_percent": 18.52
    },
    {
      "movie_id": "7XxkGNYKcCbMMjHQsDeJ3M",
      "movie_name": "Welcome to the Jungle",
      "show_id": "63457:big-movies",
      "venue": "big-movies",
      "theatre": "Big Movies - Audi 3",
      "date": "2026-07-06T08:45:00+05:45",
      "time": "",
      "seats": 349,
      "sold": 0,
      "reserved": 50,
      "available": 299,
      "gross": 10000,
      "occupancy_percent": 14.33
    },
    {
      "movie_id": "7XxkGNYKcCbMMjHQsDeJ3M",
      "movie_name": "Welcome to the Jungle",
      "show_id": "63464:big-movies",
      "venue": "big-movies",
      "theatre": "Big Movies - Audi 2",
      "date": "2026-07-06T13:45:00+05:45",
      "time": "",
      "seats": 270,
      "sold": 0,
      "reserved": 50,
      "available": 220,
      "gross": 20000,
      "occupancy_percent": 18.52
    },
    {
      "movie_id": "7XxkGNYKcCbMMjHQsDeJ3M",
      "movie_name": "Welcome to the Jungle",
      "show_id": "176047:qfx-labim",
      "venue": "qfx-labim",
      "theatre": "QFX Labim - AUDI 3",
      "date": "2026-07-06T15:00:00+05:45",
      "time": "",
      "seats": 183,
      "sold": 0,
      "reserved": 0,
      "available": 183,
      "gross": 0,
      "occupancy_percent": 0.0
    },
    {
      "movie_id": "7XxkGNYKcCbMMjHQsDeJ3M",
      "movie_name": "Welcome to the Jungle",
      "show_id": "175895:qfx-civil",
      "venue": "qfx-civil",
      "theatre": "QFX Civil - AUDI 02",
      "date": "2026-07-06T19:30:00+05:45",
      "time": "",
      "seats": 259,
      "sold": 0,
      "reserved": 0,
      "available": 259,
      "gross": 0,
      "occupancy_percent": 0.0
    },
    {
      "movie_id": "7XxkGNYKcCbMMjHQsDeJ3M",
      "movie_name": "Welcome to the Jungle",
      "show_id": "4572:kirtipur-cineplex",
      "venue": "kirtipur-cineplex",
      "theatre": "Kirtipur Cineplex - Audi-2",
      "date": "2026-07-06T14:00:00+05:45",
      "time": "",
      "seats": 101,
      "sold": 0,
      "reserved": 0,
      "available": 101,
      "gross": 0,
      "occupancy_percent": 0.0
    },
    {
      "movie_id": "7XxkGNYKcCbMMjHQsDeJ3M",
      "movie_name": "Welcome to the Jungle",
      "show_id": "4570:kirtipur-cineplex",
      "venue": "kirtipur-cineplex",
      "theatre": "Kirtipur Cineplex - Audi-1",
      "date": "2026-07-06T19:30:00+05:45",
      "time": "",
      "seats": 285,
      "sold": 0,
      "reserved": 0,
      "available": 285,
      "gross": 0,
      "occupancy_percent": 0.0
    },
    {
      "movie_id": "7XxkGNYKcCbMMjHQsDeJ3M",
      "movie_name": "Welcome to the Jungle",
      "show_id": "4569:kirtipur-cineplex",
      "venue": "kirtipur-cineplex",
      "theatre": "Kirtipur Cineplex - Audi-1",
      "date": "2026-07-06T16:30:00+05:45",
      "time": "",
      "seats": 285,
      "sold": 0,
      "reserved": 0,
      "available": 285,
      "gross": 0,
      "occupancy_percent": 0.0
    },
    {
      "movie_id": "7XxkGNYKcCbMMjHQsDeJ3M",
      "movie_name": "Welcome to the Jungle",
      "show_id": "75252:fcube",
      "venue": "fcube",
      "theatre": "FCube Cinemas - Cube 3",
      "date": "2026-07-06T12:30:00+05:45",
      "time": "",
      "seats": 212,
      "sold": 0,
      "reserved": 10,
      "available": 202,
      "gross": 4800,
      "occupancy_percent": 4.72
    },
    {
      "movie_id": "7XxkGNYKcCbMMjHQsDeJ3M",
      "movie_name": "Welcome to the Jungle",
      "show_id": "175964:qfx-durbar",
      "venue": "qfx-durbar",
      "theatre": "QFX Durbar - AUDI 1",
      "date": "2026-07-06T17:00:00+05:45",
      "time": "",
      "seats": 53,
      "sold": 0,
      "reserved": 0,
      "available": 53,
      "gross": 0,
      "occupancy_percent": 0.0
    },
    {
      "movie_id": "7XxkGNYKcCbMMjHQsDeJ3M",
      "movie_name": "Welcome to the Jungle",
      "show_id": "75259:fcube",
      "venue": "fcube",
      "theatre": "FCube Cinemas - Cube 3",
      "date": "2026-07-06T18:15:00+05:45",
      "time": "",
      "seats": 212,
      "sold": 0,
      "reserved": 10,
      "available": 202,
      "gross": 4800,
      "occupancy_percent": 4.72
    },
    {
      "movie_id": "7XxkGNYKcCbMMjHQsDeJ3M",
      "movie_name": "Welcome to the Jungle",
      "show_id": "175898:qfx-civil",
      "venue": "qfx-civil",
      "theatre": "QFX Civil - AUDI 03",
      "date": "2026-07-06T15:00:00+05:45",
      "time": "",
      "seats": 259,
      "sold": 0,
      "reserved": 0,
      "available": 259,
      "gross": 0,
      "occupancy_percent": 0.0
    },
    {
      "movie_id": "7XxkGNYKcCbMMjHQsDeJ3M",
      "movie_name": "Welcome to the Jungle",
      "show_id": "47912:bsr-movies",
      "venue": "bsr-movies",
      "theatre": "BSR Movies - Atmos 1",
      "date": "2026-07-06T14:30:00+05:45",
      "time": "",
      "seats": 192,
      "sold": 0,
      "reserved": 0,
      "available": 192,
      "gross": 0,
      "occupancy_percent": 0.0
    },
    {
      "movie_id": "7XxkGNYKcCbMMjHQsDeJ3M",
      "movie_name": "Welcome to the Jungle",
      "show_id": "47911:bsr-movies",
      "venue": "bsr-movies",
      "theatre": "BSR Movies - Atmos 1",
      "date": "2026-07-06T19:45:00+05:45",
      "time": "",
      "seats": 192,
      "sold": 0,
      "reserved": 0,
      "available": 192,
      "gross": 0,
      "occupancy_percent": 0.0
    },
    {
      "movie_id": "7XxkGNYKcCbMMjHQsDeJ3M",
      "movie_name": "Welcome to the Jungle",
      "show_id": "175926:qfx-square-mall",
      "venue": "qfx-square-mall",
      "theatre": "QFX City Square Mall - Audi 1",
      "date": "2026-07-06T15:30:00+05:45",
      "time": "",
      "seats": 177,
      "sold": 0,
      "reserved": 0,
      "available": 177,
      "gross": 0,
      "occupancy_percent": 0.0
    },
    {
      "movie_id": "7XxkGNYKcCbMMjHQsDeJ3M",
      "movie_name": "Welcome to the Jungle",
      "show_id": "175931:qfx-square-mall",
      "venue": "qfx-square-mall",
      "theatre": "QFX City Square Mall - Audi 1",
      "date": "2026-07-06T19:00:00+05:45",
      "time": "",
      "seats": 177,
      "sold": 0,
      "reserved": 0,
      "available": 177,
      "gross": 0,
      "occupancy_percent": 0.0
    },
    {
      "movie_id": "7XxkGNYKcCbMMjHQsDeJ3M",
      "movie_name": "Welcome to the Jungle",
      "show_id": "175936:qs-cinemas",
      "venue": "qs-cinemas",
      "theatre": "QFX Rising Mall - Audi 2",
      "date": "2026-07-06T16:00:00+05:45",
      "time": "",
      "seats": 129,
      "sold": 0,
      "reserved": 0,
      "available": 129,
      "gross": 0,
      "occupancy_percent": 0.0
    },
    {
      "movie_id": "7XxkGNYKcCbMMjHQsDeJ3M",
      "movie_name": "Welcome to the Jungle",
      "show_id": "28126:one-cinemas-kalimati",
      "venue": "one-cinemas-kalimati",
      "theatre": "One Cinemas Kalimati - Audi 2",
      "date": "2026-07-06T15:00:00+05:45",
      "time": "",
      "seats": 136,
      "sold": 14,
      "reserved": 0,
      "available": 122,
      "gross": 2800,
      "occupancy_percent": 10.29
    },
    {
      "movie_id": "7XxkGNYKcCbMMjHQsDeJ3M",
      "movie_name": "Welcome to the Jungle",
      "show_id": "28122:one-cinemas-kalimati",
      "venue": "one-cinemas-kalimati",
      "theatre": "One Cinemas Kalimati - Audi 1",
      "date": "2026-07-06T17:30:00+05:45",
      "time": "",
      "seats": 151,
      "sold": 14,
      "reserved": 0,
      "available": 137,
      "gross": 2800,
      "occupancy_percent": 9.27
    },
    {
      "movie_id": "7XxkGNYKcCbMMjHQsDeJ3M",
      "movie_name": "Welcome to the Jungle",
      "show_id": "176074:pokhara-cineplex",
      "venue": "pokhara-cineplex",
      "theatre": "QFX Cinemas Trade Mall - AUDI 2",
      "date": "2026-07-06T14:15:00+05:45",
      "time": "",
      "seats": 231,
      "sold": 0,
      "reserved": 0,
      "available": 231,
      "gross": 0,
      "occupancy_percent": 0.0
    },
    {
      "movie_id": "7XxkGNYKcCbMMjHQsDeJ3M",
      "movie_name": "Welcome to the Jungle",
      "show_id": "28120:one-cinemas-kalimati",
      "venue": "one-cinemas-kalimati",
      "theatre": "One Cinemas Kalimati - Audi 1",
      "date": "2026-07-06T11:45:00+05:45",
      "time": "",
      "seats": 151,
      "sold": 14,
      "reserved": 0,
      "available": 137,
      "gross": 2800,
      "occupancy_percent": 9.27
    },
    {
      "movie_id": "7XxkGNYKcCbMMjHQsDeJ3M",
      "movie_name": "Welcome to the Jungle",
      "show_id": "175906:qfx-jalma",
      "venue": "qfx-jalma",
      "theatre": "QFX Jalma, Narayangarh - AUDI 2",
      "date": "2026-07-06T18:45:00+05:45",
      "time": "",
      "seats": 265,
      "sold": 0,
      "reserved": 0,
      "available": 265,
      "gross": 0,
      "occupancy_percent": 0.0
    },
    {
      "movie_id": "7XxkGNYKcCbMMjHQsDeJ3M",
      "movie_name": "Welcome to the Jungle",
      "show_id": "175907:qfx-jalma",
      "venue": "qfx-jalma",
      "theatre": "QFX Jalma, Narayangarh - AUDI 1",
      "date": "2026-07-06T12:00:00+05:45",
      "time": "",
      "seats": 268,
      "sold": 0,
      "reserved": 0,
      "available": 268,
      "gross": 0,
      "occupancy_percent": 0.0
    },
    {
      "movie_id": "7XxkGNYKcCbMMjHQsDeJ3M",
      "movie_name": "Welcome to the Jungle",
      "show_id": "176057:chitwan-cineplex",
      "venue": "chitwan-cineplex",
      "theatre": "QFX Cinemas CG Mall - SCREEN 1",
      "date": "2026-07-06T15:15:00+05:45",
      "time": "",
      "seats": 219,
      "sold": 0,
      "reserved": 0,
      "available": 219,
      "gross": 0,
      "occupancy_percent": 0.0
    },
    {
      "movie_id": "7XxkGNYKcCbMMjHQsDeJ3M",
      "movie_name": "Welcome to the Jungle",
      "show_id": "176016:qfx-butwal",
      "venue": "qfx-butwal",
      "theatre": "QFX Butwal - AUDI 1",
      "date": "2026-07-06T18:15:00+05:45",
      "time": "",
      "seats": 176,
      "sold": 0,
      "reserved": 0,
      "available": 176,
      "gross": 0,
      "occupancy_percent": 0.0
    },
    {
      "movie_id": "7XxkGNYKcCbMMjHQsDeJ3M",
      "movie_name": "Welcome to the Jungle",
      "show_id": "176021:qfx-butwal",
      "venue": "qfx-butwal",
      "theatre": "QFX Butwal - AUDI 2",
      "date": "2026-07-06T12:15:00+05:45",
      "time": "",
      "seats": 196,
      "sold": 0,
      "reserved": 0,
      "available": 196,
      "gross": 0,
      "occupancy_percent": 0.0
    },
    {
      "movie_id": "7XxkGNYKcCbMMjHQsDeJ3M",
      "movie_name": "Welcome to the Jungle",
      "show_id": "176019:qfx-one-stop-mall",
      "venue": "qfx-one-stop-mall",
      "theatre": "QFX One Stop, Birtamod - AUDI 1",
      "date": "2026-07-06T12:00:00+05:45",
      "time": "",
      "seats": 138,
      "sold": 0,
      "reserved": 0,
      "available": 138,
      "gross": 0,
      "occupancy_percent": 0.0
    },
    {
      "movie_id": "7XxkGNYKcCbMMjHQsDeJ3M",
      "movie_name": "Welcome to the Jungle",
      "show_id": "176106:qfx-cineflix-itahari",
      "venue": "qfx-cineflix-itahari",
      "theatre": "QFX Cineflix, Itahari - Audi 2",
      "date": "2026-07-06T15:00:00+05:45",
      "time": "",
      "seats": 134,
      "sold": 0,
      "reserved": 0,
      "available": 134,
      "gross": 0,
      "occupancy_percent": 0.0
    },
    {
      "movie_id": "7XxkGNYKcCbMMjHQsDeJ3M",
      "movie_name": "Welcome to the Jungle",
      "show_id": "176023:qfx-one-stop-mall",
      "venue": "qfx-one-stop-mall",
      "theatre": "QFX One Stop, Birtamod - AUDI 2",
      "date": "2026-07-06T16:00:00+05:45",
      "time": "",
      "seats": 133,
      "sold": 0,
      "reserved": 0,
      "available": 133,
      "gross": 0,
      "occupancy_percent": 0.0
    },
    {
      "movie_id": "7XxkGNYKcCbMMjHQsDeJ3M",
      "movie_name": "Welcome to the Jungle",
      "show_id": "176105:qfx-cineflix-itahari",
      "venue": "qfx-cineflix-itahari",
      "theatre": "QFX Cineflix, Itahari - Audi 2",
      "date": "2026-07-06T11:30:00+05:45",
      "time": "",
      "seats": 134,
      "sold": 0,
      "reserved": 0,
      "available": 134,
      "gross": 0,
      "occupancy_percent": 0.0
    },
    {
      "movie_id": "7XxkGNYKcCbMMjHQsDeJ3M",
      "movie_name": "Welcome to the Jungle",
      "show_id": "2473:pathivara-cine-plaza",
      "venue": "pathivara-cine-plaza",
      "theatre": "Pathivara Cineplaza - Birtamode - Hall-B",
      "date": "2026-07-06T18:45:00+05:45",
      "time": "",
      "seats": 190,
      "sold": 0,
      "reserved": 0,
      "available": 190,
      "gross": 0,
      "occupancy_percent": 0.0
    },
    {
      "movie_id": "7XxkGNYKcCbMMjHQsDeJ3M",
      "movie_name": "Welcome to the Jungle",
      "show_id": "67893:bishwojyoti-cineplex",
      "venue": "bishwojyoti-cineplex",
      "theatre": "iNi Bishwojyoti Mall - Audi 2",
      "date": "2026-07-06T11:15:00+05:45",
      "time": "",
      "seats": 89,
      "sold": 0,
      "reserved": 0,
      "available": 89,
      "gross": 0,
      "occupancy_percent": 0.0
    },
    {
      "movie_id": "7XxkGNYKcCbMMjHQsDeJ3M",
      "movie_name": "Welcome to the Jungle",
      "show_id": "67922:ini-qbox-butwal",
      "venue": "ini-qbox-butwal",
      "theatre": "iNi Butwal - Audi 2",
      "date": "2026-07-06T13:00:00+05:45",
      "time": "",
      "seats": 196,
      "sold": 0,
      "reserved": 0,
      "available": 196,
      "gross": 0,
      "occupancy_percent": 0.0
    },
    {
      "movie_id": "7XxkGNYKcCbMMjHQsDeJ3M",
      "movie_name": "Welcome to the Jungle",
      "show_id": "67934:ini-cinemas-nb-center",
      "venue": "ini-cinemas-nb-center",
      "theatre": "iNi NB Center - Audi -2 (DTS: X)",
      "date": "2026-07-06T19:45:00+05:45",
      "time": "",
      "seats": 210,
      "sold": 0,
      "reserved": 0,
      "available": 210,
      "gross": 0,
      "occupancy_percent": 0.0
    },
    {
      "movie_id": "7XxkGNYKcCbMMjHQsDeJ3M",
      "movie_name": "Welcome to the Jungle",
      "show_id": "67906:ini-lotse-ktm",
      "venue": "ini-lotse-ktm",
      "theatre": "iNi Lotse Mall - Audi 2",
      "date": "2026-07-06T13:30:00+05:45",
      "time": "",
      "seats": 240,
      "sold": 0,
      "reserved": 0,
      "available": 240,
      "gross": 0,
      "occupancy_percent": 0.0
    },
    {
      "movie_id": "7XxkGNYKcCbMMjHQsDeJ3M",
      "movie_name": "Welcome to the Jungle",
      "show_id": "67897:ini-simara",
      "venue": "ini-simara",
      "theatre": "iNi Simara - Audi 2",
      "date": "2026-07-06T11:15:00+05:45",
      "time": "",
      "seats": 199,
      "sold": 0,
      "reserved": 0,
      "available": 199,
      "gross": 0,
      "occupancy_percent": 0.0
    },
    {
      "movie_id": "7XxkGNYKcCbMMjHQsDeJ3M",
      "movie_name": "Welcome to the Jungle",
      "show_id": "67916:ini-bhairahawa-bhatbhateni",
      "venue": "ini-bhairahawa-bhatbhateni",
      "theatre": "iNi Bhairahawa Bhatbhateni - Audi - 2 ( DTS:X )",
      "date": "2026-07-06T19:45:00+05:45",
      "time": "",
      "seats": 198,
      "sold": 0,
      "reserved": 0,
      "available": 198,
      "gross": 0,
      "occupancy_percent": 0.0
    },
    {
      "movie_id": "cXn62XZEXWjBVxPTeAt62Z",
      "movie_name": "Cocktail 2",
      "show_id": "67903:ini-lotse-ktm",
      "venue": "ini-lotse-ktm",
      "theatre": "iNi Lotse Mall - Audi 1",
      "date": "2026-07-06T16:30:00+05:45",
      "time": "",
      "seats": 240,
      "sold": 0,
      "reserved": 0,
      "available": 240,
      "gross": 0,
      "occupancy_percent": 0.0
    },
    {
      "movie_id": "cXn62XZEXWjBVxPTeAt62Z",
      "movie_name": "Cocktail 2",
      "show_id": "67928:ini-cinemas-nb-center",
      "venue": "ini-cinemas-nb-center",
      "theatre": "iNi NB Center - Audi -1 (DTS: X)",
      "date": "2026-07-06T16:00:00+05:45",
      "time": "",
      "seats": 177,
      "sold": 0,
      "reserved": 0,
      "available": 177,
      "gross": 0,
      "occupancy_percent": 0.0
    },
    {
      "movie_id": "cXn62XZEXWjBVxPTeAt62Z",
      "movie_name": "Cocktail 2",
      "show_id": "75251:fcube",
      "venue": "fcube",
      "theatre": "FCube Cinemas - Cube 2",
      "date": "2026-07-06T12:00:00+05:45",
      "time": "",
      "seats": 198,
      "sold": 0,
      "reserved": 10,
      "available": 188,
      "gross": 3800,
      "occupancy_percent": 5.05
    },
    {
      "movie_id": "cXn62XZEXWjBVxPTeAt62Z",
      "movie_name": "Cocktail 2",
      "show_id": "63471:big-movies",
      "venue": "big-movies",
      "theatre": "Big Movies - Audi 1",
      "date": "2026-07-06T19:30:00+05:45",
      "time": "",
      "seats": 279,
      "sold": 0,
      "reserved": 42,
      "available": 237,
      "gross": 16800,
      "occupancy_percent": 15.05
    },
    {
      "movie_id": "cXn62XZEXWjBVxPTeAt62Z",
      "movie_name": "Cocktail 2",
      "show_id": "63463:big-movies",
      "venue": "big-movies",
      "theatre": "Big Movies - Audi 2",
      "date": "2026-07-06T10:45:00+05:45",
      "time": "",
      "seats": 270,
      "sold": 0,
      "reserved": 50,
      "available": 220,
      "gross": 10000,
      "occupancy_percent": 18.52
    },
    {
      "movie_id": "cXn62XZEXWjBVxPTeAt62Z",
      "movie_name": "Cocktail 2",
      "show_id": "63465:big-movies",
      "venue": "big-movies",
      "theatre": "Big Movies - Audi 2",
      "date": "2026-07-06T17:00:00+05:45",
      "time": "",
      "seats": 270,
      "sold": 0,
      "reserved": 50,
      "available": 220,
      "gross": 20000,
      "occupancy_percent": 18.52
    },
    {
      "movie_id": "cXn62XZEXWjBVxPTeAt62Z",
      "movie_name": "Cocktail 2",
      "show_id": "176045:qfx-labim",
      "venue": "qfx-labim",
      "theatre": "QFX Labim - AUDI 2",
      "date": "2026-07-06T19:30:00+05:45",
      "time": "",
      "seats": 180,
      "sold": 0,
      "reserved": 0,
      "available": 180,
      "gross": 0,
      "occupancy_percent": 0.0
    },
    {
      "movie_id": "cXn62XZEXWjBVxPTeAt62Z",
      "movie_name": "Cocktail 2",
      "show_id": "47906:bsr-movies",
      "venue": "bsr-movies",
      "theatre": "BSR Movies - Atmos 1",
      "date": "2026-07-06T11:30:00+05:45",
      "time": "",
      "seats": 192,
      "sold": 0,
      "reserved": 0,
      "available": 192,
      "gross": 0,
      "occupancy_percent": 0.0
    },
    {
      "movie_id": "cXn62XZEXWjBVxPTeAt62Z",
      "movie_name": "Cocktail 2",
      "show_id": "176038:qfx-chhaya",
      "venue": "qfx-chhaya",
      "theatre": "QFX Chhaya - AUDI 2",
      "date": "2026-07-06T13:30:00+05:45",
      "time": "",
      "seats": 150,
      "sold": 0,
      "reserved": 0,
      "available": 150,
      "gross": 0,
      "occupancy_percent": 0.0
    },
    {
      "movie_id": "cXn62XZEXWjBVxPTeAt62Z",
      "movie_name": "Cocktail 2",
      "show_id": "28125:one-cinemas-kalimati",
      "venue": "one-cinemas-kalimati",
      "theatre": "One Cinemas Kalimati - Audi 2",
      "date": "2026-07-06T12:15:00+05:45",
      "time": "",
      "seats": 136,
      "sold": 14,
      "reserved": 0,
      "available": 122,
      "gross": 2800,
      "occupancy_percent": 10.29
    },
    {
      "movie_id": "cXn62XZEXWjBVxPTeAt62Z",
      "movie_name": "Cocktail 2",
      "show_id": "4573:kirtipur-cineplex",
      "venue": "kirtipur-cineplex",
      "theatre": "Kirtipur Cineplex - Audi-2",
      "date": "2026-07-06T17:00:00+05:45",
      "time": "",
      "seats": 101,
      "sold": 0,
      "reserved": 0,
      "available": 101,
      "gross": 0,
      "occupancy_percent": 0.0
    },
    {
      "movie_id": "cXn62XZEXWjBVxPTeAt62Z",
      "movie_name": "Cocktail 2",
      "show_id": "175908:qfx-jalma",
      "venue": "qfx-jalma",
      "theatre": "QFX Jalma, Narayangarh - AUDI 2",
      "date": "2026-07-06T12:15:00+05:45",
      "time": "",
      "seats": 265,
      "sold": 2,
      "reserved": 0,
      "available": 263,
      "gross": 760,
      "occupancy_percent": 0.75
    },
    {
      "movie_id": "cXn62XZEXWjBVxPTeAt62Z",
      "movie_name": "Cocktail 2",
      "show_id": "176059:chitwan-cineplex",
      "venue": "chitwan-cineplex",
      "theatre": "QFX Cinemas CG Mall - SCREEN 2",
      "date": "2026-07-06T15:30:00+05:45",
      "time": "",
      "seats": 143,
      "sold": 0,
      "reserved": 0,
      "available": 143,
      "gross": 0,
      "occupancy_percent": 0.0
    },
    {
      "movie_id": "cXn62XZEXWjBVxPTeAt62Z",
      "movie_name": "Cocktail 2",
      "show_id": "67923:ini-qbox-butwal",
      "venue": "ini-qbox-butwal",
      "theatre": "iNi Butwal - Audi 2",
      "date": "2026-07-06T16:15:00+05:45",
      "time": "",
      "seats": 196,
      "sold": 0,
      "reserved": 0,
      "available": 196,
      "gross": 0,
      "occupancy_percent": 0.0
    },
    {
      "movie_id": "cXn62XZEXWjBVxPTeAt62Z",
      "movie_name": "Cocktail 2",
      "show_id": "175894:qfx-civil",
      "venue": "qfx-civil",
      "theatre": "QFX Civil - AUDI 02",
      "date": "2026-07-06T16:15:00+05:45",
      "time": "",
      "seats": 259,
      "sold": 0,
      "reserved": 0,
      "available": 259,
      "gross": 0,
      "occupancy_percent": 0.0
    },
    {
      "movie_id": "cXn62XZEXWjBVxPTeAt62Z",
      "movie_name": "Cocktail 2",
      "show_id": "176073:pokhara-cineplex",
      "venue": "pokhara-cineplex",
      "theatre": "QFX Cinemas Trade Mall - AUDI 2",
      "date": "2026-07-06T11:15:00+05:45",
      "time": "",
      "seats": 231,
      "sold": 0,
      "reserved": 0,
      "available": 231,
      "gross": 0,
      "occupancy_percent": 0.0
    },
    {
      "movie_id": "cXn62XZEXWjBVxPTeAt62Z",
      "movie_name": "Cocktail 2",
      "show_id": "175897:qfx-civil",
      "venue": "qfx-civil",
      "theatre": "QFX Civil - AUDI 03",
      "date": "2026-07-06T11:45:00+05:45",
      "time": "",
      "seats": 259,
      "sold": 0,
      "reserved": 0,
      "available": 259,
      "gross": 0,
      "occupancy_percent": 0.0
    },
    {
      "movie_id": "cXn62XZEXWjBVxPTeAt62Z",
      "movie_name": "Cocktail 2",
      "show_id": "67894:bishwojyoti-cineplex",
      "venue": "bishwojyoti-cineplex",
      "theatre": "iNi Bishwojyoti Mall - Audi 2",
      "date": "2026-07-06T14:30:00+05:45",
      "time": "",
      "seats": 89,
      "sold": 0,
      "reserved": 0,
      "available": 89,
      "gross": 0,
      "occupancy_percent": 0.0
    },
    {
      "movie_id": "cXn62XZEXWjBVxPTeAt62Z",
      "movie_name": "Cocktail 2",
      "show_id": "67915:ini-bhairahawa-bhatbhateni",
      "venue": "ini-bhairahawa-bhatbhateni",
      "theatre": "iNi Bhairahawa Bhatbhateni - Audi - 2 ( DTS:X )",
      "date": "2026-07-06T16:30:00+05:45",
      "time": "",
      "seats": 198,
      "sold": 0,
      "reserved": 0,
      "available": 198,
      "gross": 0,
      "occupancy_percent": 0.0
    },
    {
      "movie_id": "cXn62XZEXWjBVxPTeAt62Z",
      "movie_name": "Cocktail 2",
      "show_id": "2472:pathivara-cine-plaza",
      "venue": "pathivara-cine-plaza",
      "theatre": "Pathivara Cineplaza - Birtamode - Hall-B",
      "date": "2026-07-06T14:30:00+05:45",
      "time": "",
      "seats": 190,
      "sold": 0,
      "reserved": 0,
      "available": 190,
      "gross": 0,
      "occupancy_percent": 0.0
    },
    {
      "movie_id": "RaQGMX24uSiXsJSVgBYrqK",
      "movie_name": "Minions & Monsters",
      "show_id": "75253:fcube",
      "venue": "fcube",
      "theatre": "FCube Cinemas - Cube 1",
      "date": "2026-07-06T14:15:00+05:45",
      "time": "",
      "seats": 210,
      "sold": 1,
      "reserved": 10,
      "available": 199,
      "gross": 4730,
      "occupancy_percent": 5.24
    },
    {
      "movie_id": "RaQGMX24uSiXsJSVgBYrqK",
      "movie_name": "Minions & Monsters",
      "show_id": "67927:ini-cinemas-nb-center",
      "venue": "ini-cinemas-nb-center",
      "theatre": "iNi NB Center - Audi -1 (DTS: X)",
      "date": "2026-07-06T14:00:00+05:45",
      "time": "",
      "seats": 177,
      "sold": 0,
      "reserved": 0,
      "available": 177,
      "gross": 0,
      "occupancy_percent": 0.0
    },
    {
      "movie_id": "RaQGMX24uSiXsJSVgBYrqK",
      "movie_name": "Minions & Monsters",
      "show_id": "176034:qfx-chhaya",
      "venue": "qfx-chhaya",
      "theatre": "QFX Chhaya - AUDI 1",
      "date": "2026-07-06T17:15:00+05:45",
      "time": "",
      "seats": 112,
      "sold": 2,
      "reserved": 0,
      "available": 110,
      "gross": 940,
      "occupancy_percent": 1.79
    },
    {
      "movie_id": "RaQGMX24uSiXsJSVgBYrqK",
      "movie_name": "Minions & Monsters",
      "show_id": "67905:ini-lotse-ktm",
      "venue": "ini-lotse-ktm",
      "theatre": "iNi Lotse Mall - Audi 2",
      "date": "2026-07-06T11:30:00+05:45",
      "time": "",
      "seats": 240,
      "sold": 0,
      "reserved": 0,
      "available": 240,
      "gross": 0,
      "occupancy_percent": 0.0
    },
    {
      "movie_id": "RaQGMX24uSiXsJSVgBYrqK",
      "movie_name": "Minions & Monsters",
      "show_id": "63469:big-movies",
      "venue": "big-movies",
      "theatre": "Big Movies - Audi 1",
      "date": "2026-07-06T14:00:00+05:45",
      "time": "",
      "seats": 279,
      "sold": 0,
      "reserved": 42,
      "available": 237,
      "gross": 18900,
      "occupancy_percent": 15.05
    },
    {
      "movie_id": "RaQGMX24uSiXsJSVgBYrqK",
      "movie_name": "Minions & Monsters",
      "show_id": "176036:qfx-chhaya",
      "venue": "qfx-chhaya",
      "theatre": "QFX Chhaya - AUDI 2",
      "date": "2026-07-06T11:15:00+05:45",
      "time": "",
      "seats": 150,
      "sold": 0,
      "reserved": 0,
      "available": 150,
      "gross": 0,
      "occupancy_percent": 0.0
    },
    {
      "movie_id": "RaQGMX24uSiXsJSVgBYrqK",
      "movie_name": "Minions & Monsters",
      "show_id": "175965:qfx-durbar",
      "venue": "qfx-durbar",
      "theatre": "QFX Durbar - AUDI 1",
      "date": "2026-07-06T14:45:00+05:45",
      "time": "",
      "seats": 53,
      "sold": 0,
      "reserved": 0,
      "available": 53,
      "gross": 0,
      "occupancy_percent": 0.0
    },
    {
      "movie_id": "RaQGMX24uSiXsJSVgBYrqK",
      "movie_name": "Minions & Monsters",
      "show_id": "176039:qfx-labim",
      "venue": "qfx-labim",
      "theatre": "QFX Labim - AUDI 2",
      "date": "2026-07-06T11:00:00+05:45",
      "time": "",
      "seats": 180,
      "sold": 0,
      "reserved": 0,
      "available": 180,
      "gross": 0,
      "occupancy_percent": 0.0
    },
    {
      "movie_id": "RaQGMX24uSiXsJSVgBYrqK",
      "movie_name": "Minions & Monsters",
      "show_id": "176037:qfx-labim",
      "venue": "qfx-labim",
      "theatre": "QFX Labim - AUDI 1",
      "date": "2026-07-06T16:30:00+05:45",
      "time": "",
      "seats": 182,
      "sold": 0,
      "reserved": 0,
      "available": 182,
      "gross": 0,
      "occupancy_percent": 0.0
    },
    {
      "movie_id": "RaQGMX24uSiXsJSVgBYrqK",
      "movie_name": "Minions & Monsters",
      "show_id": "47913:bsr-movies",
      "venue": "bsr-movies",
      "theatre": "BSR Movies - Atmos 1",
      "date": "2026-07-06T17:45:00+05:45",
      "time": "",
      "seats": 192,
      "sold": 0,
      "reserved": 0,
      "available": 192,
      "gross": 0,
      "occupancy_percent": 0.0
    },
    {
      "movie_id": "RaQGMX24uSiXsJSVgBYrqK",
      "movie_name": "Minions & Monsters",
      "show_id": "67890:bishwojyoti-cineplex",
      "venue": "bishwojyoti-cineplex",
      "theatre": "iNi Bishwojyoti Mall - Audi 1",
      "date": "2026-07-06T14:15:00+05:45",
      "time": "",
      "seats": 201,
      "sold": 0,
      "reserved": 0,
      "available": 201,
      "gross": 0,
      "occupancy_percent": 0.0
    },
    {
      "movie_id": "RaQGMX24uSiXsJSVgBYrqK",
      "movie_name": "Minions & Monsters",
      "show_id": "67898:ini-simara",
      "venue": "ini-simara",
      "theatre": "iNi Simara - Audi 2",
      "date": "2026-07-06T14:30:00+05:45",
      "time": "",
      "seats": 199,
      "sold": 0,
      "reserved": 0,
      "available": 199,
      "gross": 0,
      "occupancy_percent": 0.0
    },
    {
      "movie_id": "RaQGMX24uSiXsJSVgBYrqK",
      "movie_name": "Minions & Monsters",
      "show_id": "175934:qs-cinemas",
      "venue": "qs-cinemas",
      "theatre": "QFX Rising Mall - Audi 2",
      "date": "2026-07-06T11:00:00+05:45",
      "time": "",
      "seats": 129,
      "sold": 0,
      "reserved": 0,
      "available": 129,
      "gross": 0,
      "occupancy_percent": 0.0
    },
    {
      "movie_id": "RaQGMX24uSiXsJSVgBYrqK",
      "movie_name": "Minions & Monsters",
      "show_id": "28124:one-cinemas-kalimati",
      "venue": "one-cinemas-kalimati",
      "theatre": "One Cinemas Kalimati - Audi 2",
      "date": "2026-07-06T10:00:00+05:45",
      "time": "",
      "seats": 136,
      "sold": 14,
      "reserved": 0,
      "available": 122,
      "gross": 3500,
      "occupancy_percent": 10.29
    },
    {
      "movie_id": "RaQGMX24uSiXsJSVgBYrqK",
      "movie_name": "Minions & Monsters",
      "show_id": "175893:qfx-civil",
      "venue": "qfx-civil",
      "theatre": "QFX Civil - AUDI 02",
      "date": "2026-07-06T11:30:00+05:45",
      "time": "",
      "seats": 259,
      "sold": 0,
      "reserved": 0,
      "available": 259,
      "gross": 0,
      "occupancy_percent": 0.0
    },
    {
      "movie_id": "RaQGMX24uSiXsJSVgBYrqK",
      "movie_name": "Minions & Monsters",
      "show_id": "176003:qfx-square-mall",
      "venue": "qfx-square-mall",
      "theatre": "QFX City Square Mall - Audi 03",
      "date": "2026-07-06T15:00:00+05:45",
      "time": "",
      "seats": 139,
      "sold": 0,
      "reserved": 0,
      "available": 139,
      "gross": 0,
      "occupancy_percent": 0.0
    },
    {
      "movie_id": "RaQGMX24uSiXsJSVgBYrqK",
      "movie_name": "Minions & Monsters",
      "show_id": "67914:ini-bhairahawa-bhatbhateni",
      "venue": "ini-bhairahawa-bhatbhateni",
      "theatre": "iNi Bhairahawa Bhatbhateni - Audi - 2 ( DTS:X )",
      "date": "2026-07-06T14:30:00+05:45",
      "time": "",
      "seats": 198,
      "sold": 0,
      "reserved": 0,
      "available": 198,
      "gross": 0,
      "occupancy_percent": 0.0
    },
    {
      "movie_id": "RaQGMX24uSiXsJSVgBYrqK",
      "movie_name": "Minions & Monsters",
      "show_id": "175998:qfx-square-mall",
      "venue": "qfx-square-mall",
      "theatre": "QFX City Square Mall - Audi 2",
      "date": "2026-07-06T11:45:00+05:45",
      "time": "",
      "seats": 165,
      "sold": 0,
      "reserved": 0,
      "available": 165,
      "gross": 0,
      "occupancy_percent": 0.0
    },
    {
      "movie_id": "RaQGMX24uSiXsJSVgBYrqK",
      "movie_name": "Minions & Monsters",
      "show_id": "176102:qfx-cineflix-itahari",
      "venue": "qfx-cineflix-itahari",
      "theatre": "QFX Cineflix, Itahari - Audi 1",
      "date": "2026-07-06T17:00:00+05:45",
      "time": "",
      "seats": 134,
      "sold": 0,
      "reserved": 0,
      "available": 134,
      "gross": 0,
      "occupancy_percent": 0.0
    },
    {
      "movie_id": "RaQGMX24uSiXsJSVgBYrqK",
      "movie_name": "Minions & Monsters",
      "show_id": "176075:pokhara-cineplex",
      "venue": "pokhara-cineplex",
      "theatre": "QFX Cinemas Trade Mall - AUDI 2",
      "date": "2026-07-06T17:30:00+05:45",
      "time": "",
      "seats": 231,
      "sold": 0,
      "reserved": 0,
      "available": 231,
      "gross": 0,
      "occupancy_percent": 0.0
    },
    {
      "movie_id": "RaQGMX24uSiXsJSVgBYrqK",
      "movie_name": "Minions & Monsters",
      "show_id": "176020:qfx-butwal",
      "venue": "qfx-butwal",
      "theatre": "QFX Butwal - AUDI 2",
      "date": "2026-07-06T15:30:00+05:45",
      "time": "",
      "seats": 196,
      "sold": 0,
      "reserved": 0,
      "available": 196,
      "gross": 0,
      "occupancy_percent": 0.0
    },
    {
      "movie_id": "RaQGMX24uSiXsJSVgBYrqK",
      "movie_name": "Minions & Monsters",
      "show_id": "67921:ini-qbox-butwal",
      "venue": "ini-qbox-butwal",
      "theatre": "iNi Butwal - Audi 2",
      "date": "2026-07-06T11:00:00+05:45",
      "time": "",
      "seats": 196,
      "sold": 0,
      "reserved": 0,
      "available": 196,
      "gross": 0,
      "occupancy_percent": 0.0
    },
    {
      "movie_id": "tMrVmuJXzakB8CCZmRNJBG",
      "movie_name": "OBSESSION",
      "show_id": "75256:fcube",
      "venue": "fcube",
      "theatre": "FCube Cinemas - Cube 1",
      "date": "2026-07-06T16:15:00+05:45",
      "time": "",
      "seats": 210,
      "sold": 0,
      "reserved": 10,
      "available": 200,
      "gross": 3800,
      "occupancy_percent": 4.76
    },
    {
      "movie_id": "tMrVmuJXzakB8CCZmRNJBG",
      "movie_name": "OBSESSION",
      "show_id": "63468:big-movies",
      "venue": "big-movies",
      "theatre": "Big Movies - Audi 1",
      "date": "2026-07-06T11:45:00+05:45",
      "time": "",
      "seats": 279,
      "sold": 0,
      "reserved": 42,
      "available": 237,
      "gross": 16800,
      "occupancy_percent": 15.05
    },
    {
      "movie_id": "tMrVmuJXzakB8CCZmRNJBG",
      "movie_name": "OBSESSION",
      "show_id": "176035:qfx-chhaya",
      "venue": "qfx-chhaya",
      "theatre": "QFX Chhaya - AUDI 1",
      "date": "2026-07-06T19:30:00+05:45",
      "time": "",
      "seats": 112,
      "sold": 0,
      "reserved": 0,
      "available": 112,
      "gross": 0,
      "occupancy_percent": 0.0
    },
    {
      "movie_id": "tMrVmuJXzakB8CCZmRNJBG",
      "movie_name": "OBSESSION",
      "show_id": "175939:qs-cinemas",
      "venue": "qs-cinemas",
      "theatre": "QFX Rising Mall - Audi 01",
      "date": "2026-07-06T14:30:00+05:45",
      "time": "",
      "seats": 182,
      "sold": 4,
      "reserved": 0,
      "available": 178,
      "gross": 1400,
      "occupancy_percent": 2.2
    },
    {
      "movie_id": "tMrVmuJXzakB8CCZmRNJBG",
      "movie_name": "OBSESSION",
      "show_id": "175927:qfx-square-mall",
      "venue": "qfx-square-mall",
      "theatre": "QFX City Square Mall - Audi 2",
      "date": "2026-07-06T14:00:00+05:45",
      "time": "",
      "seats": 165,
      "sold": 2,
      "reserved": 0,
      "available": 163,
      "gross": 700,
      "occupancy_percent": 1.21
    },
    {
      "movie_id": "tMrVmuJXzakB8CCZmRNJBG",
      "movie_name": "OBSESSION",
      "show_id": "175892:qfx-civil",
      "venue": "qfx-civil",
      "theatre": "QFX Civil - AUDI 02",
      "date": "2026-07-06T13:45:00+05:45",
      "time": "",
      "seats": 259,
      "sold": 0,
      "reserved": 0,
      "available": 259,
      "gross": 0,
      "occupancy_percent": 0.0
    },
    {
      "movie_id": "tMrVmuJXzakB8CCZmRNJBG",
      "movie_name": "OBSESSION",
      "show_id": "67925:ini-cinemas-nb-center",
      "venue": "ini-cinemas-nb-center",
      "theatre": "iNi NB Center - Audi -1 (DTS: X)",
      "date": "2026-07-06T08:15:00+05:45",
      "time": "",
      "seats": 177,
      "sold": 0,
      "reserved": 0,
      "available": 177,
      "gross": 0,
      "occupancy_percent": 0.0
    },
    {
      "movie_id": "2xzU5oXd3N5urfFfabDAKo",
      "movie_name": "Colony",
      "show_id": "176046:qfx-labim",
      "venue": "qfx-labim",
      "theatre": "QFX Labim - AUDI 3",
      "date": "2026-07-06T12:00:00+05:45",
      "time": "",
      "seats": 183,
      "sold": 0,
      "reserved": 0,
      "available": 183,
      "gross": 0,
      "occupancy_percent": 0.0
    },
    {
      "movie_id": "2xzU5oXd3N5urfFfabDAKo",
      "movie_name": "Colony",
      "show_id": "176048:qfx-chhaya",
      "venue": "qfx-chhaya",
      "theatre": "QFX Chhaya - AUDI 03",
      "date": "2026-07-06T18:15:00+05:45",
      "time": "",
      "seats": 110,
      "sold": 0,
      "reserved": 0,
      "available": 110,
      "gross": 0,
      "occupancy_percent": 0.0
    },
    {
      "movie_id": "2xzU5oXd3N5urfFfabDAKo",
      "movie_name": "Colony",
      "show_id": "176014:qfx-square-mall",
      "venue": "qfx-square-mall",
      "theatre": "QFX City Square Mall - Audi 03",
      "date": "2026-07-06T17:15:00+05:45",
      "time": "",
      "seats": 139,
      "sold": 0,
      "reserved": 0,
      "available": 139,
      "gross": 0,
      "occupancy_percent": 0.0
    },
    {
      "movie_id": "2xzU5oXd3N5urfFfabDAKo",
      "movie_name": "Colony",
      "show_id": "75254:fcube",
      "venue": "fcube",
      "theatre": "FCube Cinemas - Cube 2",
      "date": "2026-07-06T15:00:00+05:45",
      "time": "",
      "seats": 198,
      "sold": 0,
      "reserved": 13,
      "available": 185,
      "gross": 4940,
      "occupancy_percent": 6.57
    },
    {
      "movie_id": "jnNDFUXs4UZv2W2oF2CWVj",
      "movie_name": "Toy Story 5",
      "show_id": "176032:qfx-chhaya",
      "venue": "qfx-chhaya",
      "theatre": "QFX Chhaya - AUDI 1",
      "date": "2026-07-06T14:45:00+05:45",
      "time": "",
      "seats": 112,
      "sold": 0,
      "reserved": 0,
      "available": 112,
      "gross": 0,
      "occupancy_percent": 0.0
    },
    {
      "movie_id": "jnNDFUXs4UZv2W2oF2CWVj",
      "movie_name": "Toy Story 5",
      "show_id": "176033:qfx-labim",
      "venue": "qfx-labim",
      "theatre": "QFX Labim - AUDI 1",
      "date": "2026-07-06T14:15:00+05:45",
      "time": "",
      "seats": 182,
      "sold": 0,
      "reserved": 0,
      "available": 182,
      "gross": 0,
      "occupancy_percent": 0.0
    }
  ]
}